scripts/__init__.py
scripts/main.py
apk_launcher-1.0.0.dist-info/METADATA
apk_launcher-1.0.0.dist-info/WHEEL
apk_launcher-1.0.0.dist-info/entry_points.txt
apk_launcher-1.0.0.dist-info/top_level.txt
apk_launcher-1.0.0.dist-info/RECORD
