Metadata-Version: 2.1
Name: apk-launcher
Version: 1.0.0
Summary: Easy to handle your apk
Home-page: https://github.com/ksg97031/apk-launcher
Author: ksg97031
Author-email: ksg97031@gmail.com
License: UNKNOWN
Platform: UNKNOWN
Classifier: Programming Language :: Python :: 3
Classifier: License :: OSI Approved :: MIT License
Classifier: Operating System :: OS Independent
Requires-Python: >=3
Requires-Dist: androguard
Requires-Dist: adb
Requires-Dist: click
Requires-Dist: rsa
